Workbook

Sheet Sales Data
A2: Order_ID | B2: Order_Date | C2: Employee_ID | D2: Product_ID | E2: Region | F2: Customer_Type | G2: Quantity | H2: Unit_Price | I2: Discount | J2: Gross Sales | K2: Discount Amount | L2: Net Sales | M2: Employee_Name | N2: Product Name | O2: Category | P2: Total cost | Q2: Profit | R2: Month | S2: Order Status
A3: ORD101 | B3: 01-10-2026 | C3: E101 | D3: P101 | E3: North | F3: Retail | G3: 10 | H3: 1200 | I3: 0.05 | J3: =Table1[[#This Row],[Quantity]]*Table1[[#This Row],[Unit_Price]] -> 12000 | K3: =Table1[[#This Row],[Discount]]*Table1[[#This Row],[Gross Sales]] -> 600 | L3: =Table1[[#This Row],[Gross Sales]]-Table1[[#This Row],[Discount]] -> 11999.95 | M3: Karan
A4: ORD102 | B4: 02-10-2026 | C4: E102 | D4: P103 | E4: West | F4: Corporate | G4: 25 | H4: 800 | I4: 0.1 | J4: =Table1[[#This Row],[Quantity]]*Table1[[#This Row],[Unit_Price]] -> 20000 | K4: =Table1[[#This Row],[Discount]]*Table1[[#This Row],[Gross Sales]] -> 2000 | L4: =Table1[[#This Row],[Gross Sales]]-Table1[[#This Row],[Discount]] -> 19999.9 | M4: =_xlfn.XLOOKUP(C3,Employee_Master!A:A,Employee_Master!B:B,"Not Found") -> Rahul
A5: ORD103 | B5: 02-10-2026 | C5: E103 | D5: P102 | E5: South | F5: Retail | G5: 8 | H5: 1500 | I5: 0 | J5: =Table1[[#This Row],[Quantity]]*Table1[[#This Row],[Unit_Price]] -> 12000 | K5: =Table1[[#This Row],[Discount]]*Table1[[#This Row],[Gross Sales]] -> 0 | L5: =Table1[[#This Row],[Gross Sales]]-Table1[[#This Row],[Discount]] -> 12000 | M5: =_xlfn.XLOOKUP(C4,Employee_Master!A:A,Employee_Master!B:B,"Not Found") -> Priya
A6: ORD104 | B6: 03-10-2026 | C6: E104 | D6: P104 | E6: East | F6: Corporate | G6: 15 | H6: 600 | I6: 0.05 | J6: =Table1[[#This Row],[Quantity]]*Table1[[#This Row],[Unit_Price]] -> 9000 | K6: =Table1[[#This Row],[Discount]]*Table1[[#This Row],[Gross Sales]] -> 450 | L6: =Table1[[#This Row],[Gross Sales]]-Table1[[#This Row],[Discount]] -> 8999.95 | M6: =_xlfn.XLOOKUP(C5,Employee_Master!A:A,Employee_Master!B:B,"Not Found") -> Amit
A7: ORD105 | B7: 04-10-2026 | C7: E101 | D7: P105 | E7: North | F7: Retail | G7: 30 | H7: 250 | I7: 0 | J7: =Table1[[#This Row],[Quantity]]*Table1[[#This Row],[Unit_Price]] -> 7500 | K7: =Table1[[#This Row],[Discount]]*Table1[[#This Row],[Gross Sales]] -> 0 | L7: =Table1[[#This Row],[Gross Sales]]-Table1[[#This Row],[Discount]] -> 7500 | M7: =_xlfn.XLOOKUP(C6,Employee_Master!A:A,Employee_Master!B:B,"Not Found") -> Neha
A8: ORD106 | B8: 05-10-2026 | C8: E105 | D8: P106 | E8: West | F8: Corporate | G8: 12 | H8: 2200 | I8: 0.15 | J8: =Table1[[#This Row],[Quantity]]*Table1[[#This Row],[Unit_Price]] -> 26400 | K8: =Table1[[#This Row],[Discount]]*Table1[[#This Row],[Gross Sales]] -> 3960 | L8: =Table1[[#This Row],[Gross Sales]]-Table1[[#This Row],[Discount]] -> 26399.85 | M8: =_xlfn.XLOOKUP(C7,Employee_Master!A:A,Employee_Master!B:B,"Not Found") -> Rahul
A9: ORD107 | B9: 06-10-2026 | C9: E102 | D9: P101 | E9: South | F9: Retail | G9: 6 | H9: 1200 | I9: 0.05 | J9: =Table1[[#This Row],[Quantity]]*Table1[[#This Row],[Unit_Price]] -> 7200 | K9: =Table1[[#This Row],[Discount]]*Table1[[#This Row],[Gross Sales]] -> 360 | L9: =Table1[[#This Row],[Gross Sales]]-Table1[[#This Row],[Discount]] -> 7199.95 | M9: =_xlfn.XLOOKUP(C8,Employee_Master!A:A,Employee_Master!B:B,"Not Found") -> Karan
A10: ORD108 | B10: 07-10-2026 | C10: E106 | D10: P107 | E10: East | F10: Retail | G10: 40 | H10: 150 | I10: 0 | J10: =Table1[[#This Row],[Quantity]]*Table1[[#This Row],[Unit_Price]] -> 6000 | K10: =Table1[[#This Row],[Discount]]*Table1[[#This Row],[Gross Sales]] -> 0 | L10: =Table1[[#This Row],[Gross Sales]]-Table1[[#This Row],[Discount]] -> 6000 | M10: =_xlfn.XLOOKUP(C9,Employee_Master!A:A,Employee_Master!B:B,"Not Found") -> Priya
A11: ORD109 | B11: 08-10-2026 | C11: E103 | D11: P103 | E11: North | F11: Corporate | G11: 20 | H11: 800 | I11: 0.1 | J11: =Table1[[#This Row],[Quantity]]*Table1[[#This Row],[Unit_Price]] -> 16000 | K11: =Table1[[#This Row],[Discount]]*Table1[[#This Row],[Gross Sales]] -> 1600 | L11: =Table1[[#This Row],[Gross Sales]]-Table1[[#This Row],[Discount]] -> 15999.9 | M11: =_xlfn.XLOOKUP(C10,Employee_Master!A:A,Employee_Master!B:B,"Not Found") -> Pooja
A12: ORD110 | B12: 09-10-2026 | C12: E104 | D12: P108 | E12: West | F12: Retail | G12: 5 | H12: 3000 | I12: 0.05 | J12: =Table1[[#This Row],[Quantity]]*Table1[[#This Row],[Unit_Price]] -> 15000 | K12: =Table1[[#This Row],[Discount]]*Table1[[#This Row],[Gross Sales]] -> 750 | L12: =Table1[[#This Row],[Gross Sales]]-Table1[[#This Row],[Discount]] -> 14999.95 | M12: =_xlfn.XLOOKUP(C11,Employee_Master!A:A,Employee_Master!B:B,"Not Found") -> Amit
A13: ORD111 | B13: 10-10-2026 | C13: E105 | D13: P102 | E13: South | F13: Corporate | G13: 14 | H13: 1500 | I13: 0.1 | J13: =Table1[[#This Row],[Quantity]]*Table1[[#This Row],[Unit_Price]] -> 21000 | K13: =Table1[[#This Row],[Discount]]*Table1[[#This Row],[Gross Sales]] -> 2100 | L13: =Table1[[#This Row],[Gross Sales]]-Table1[[#This Row],[Discount]] -> 20999.9 | M13: =_xlfn.XLOOKUP(C12,Employee_Master!A:A,Employee_Master!B:B,"Not Found") -> Neha
A14: ORD112 | B14: 11-10-2026 | C14: E101 | D14: P104 | E14: East | F14: Retail | G14: 22 | H14: 600 | I14: 0 | J14: =Table1[[#This Row],[Quantity]]*Table1[[#This Row],[Unit_Price]] -> 13200 | K14: =Table1[[#This Row],[Discount]]*Table1[[#This Row],[Gross Sales]] -> 0 | L14: =Table1[[#This Row],[Gross Sales]]-Table1[[#This Row],[Discount]] -> 13200 | M14: =_xlfn.XLOOKUP(C13,Employee_Master!A:A,Employee_Master!B:B,"Not Found") -> Karan
A15: ORD113 | B15: 12-10-2026 | C15: E106 | D15: P105 | E15: North | F15: Corporate | G15: 50 | H15: 250 | I15: 0.05 | J15: =Table1[[#This Row],[Quantity]]*Table1[[#This Row],[Unit_Price]] -> 12500 | K15: =Table1[[#This Row],[Discount]]*Table1[[#This Row],[Gross Sales]] -> 625 | L15: =Table1[[#This Row],[Gross Sales]]-Table1[[#This Row],[Discount]] -> 12499.95 | M15: =_xlfn.XLOOKUP(C14,Employee_Master!A:A,Employee_Master!B:B,"Not Found") -> Rahul
... A22: ORD120 | B22: 19-10-2026 | C22: E102 | D22: P104 | E22: East | F22: Retail | G22: 16 | H22: 600 | I22: 0.05 | J22: =Table1[[#This Row],[Quantity]]*Table1[[#This Row],[Unit_Price]] -> 9600 | K22: =Table1[[#This Row],[Discount]]*Table1[[#This Row],[Gross Sales]] -> 480 | L22: =Table1[[#This Row],[Gross Sales]]-Table1[[#This Row],[Discount]] -> 9599.95 | M22: =_xlfn.XLOOKUP(C21,Employee_Master!A:A,Employee_Master!B:B,"Not Found") -> Rahul
N23: =_xlfn.XLOOKUP(D2,Product_Master!A:A,Product_Master!B:B,"Not Found") -> Product_Name
G24: =SUM(G3:G22) -> 410 | N24: =_xlfn.XLOOKUP(D3,Product_Master!A:A,Product_Master!B:B,"Not Found") -> Laptop
A25: SUM | N25: =_xlfn.XLOOKUP(D4,Product_Master!A:A,Product_Master!B:B,"Not Found") -> Keyboard
A26: SUMIFS | N26: =_xlfn.XLOOKUP(D5,Product_Master!A:A,Product_Master!B:B,"Not Found") -> Monitor
H27: Total sales | N27: =_xlfn.XLOOKUP(D6,Product_Master!A:A,Product_Master!B:B,"Not Found") -> Mouse | P27: Is table mein practice karo: SUM, SUMIFS, COUNTIFS, IF, XLOOKUP, VLOOKUP, INDEX-MATCH, IFERROR, TEXT, Pivot Table aur charts.
A28: Q1. Total sales kitni hui? | N28: =_xlfn.XLOOKUP(D7,Product_Master!A:A,Product_Master!B:B,"Not Found") -> Notebook
A29: SUM ka use karke total Net Sales nikalo. | N29: =_xlfn.XLOOKUP(D8,Product_Master!A:A,Product_Master!B:B,"Not Found") -> Printer
A30: LEVEL 1 · MUST KNOW | N30: =_xlfn.XLOOKUP(D9,Product_Master!A:A,Product_Master!B:B,"Not Found") -> Laptop
A31: Q2. North region ki total sales kitni hain? | N31: =_xlfn.XLOOKUP(D10,Product_Master!A:A,Product_Master!B:B,"Not Found") -> Pen
A32: SUMIFS ka use karo. | N32: =_xlfn.XLOOKUP(D11,Product_Master!A:A,Product_Master!B:B,"Not Found") -> Keyboard
A33: LEVEL 1 · MUST KNOW | N33: =_xlfn.XLOOKUP(D12,Product_Master!A:A,Product_Master!B:B,"Not Found") -> Office Chair
A34: Q3. Corporate customers ke total orders kitne hain? | N34: =_xlfn.XLOOKUP(D13,Product_Master!A:A,Product_Master!B:B,"Not Found") -> Monitor
A35: COUNTIF ka use karo. | N35: =_xlfn.XLOOKUP(D14,Product_Master!A:A,Product_Master!B:B,"Not Found") -> Mouse
A36: LEVEL 2 · INTERVIEW FAVORITE | N36: =_xlfn.XLOOKUP(D15,Product_Master!A:A,Product_Master!B:B,"Not Found") -> Notebook
A37: Q4. Kis employee ne ₹10,000 se zyada Net Sales wale kitne orders kiye? | N37: =_xlfn.XLOOKUP(D16,Product_Master!A:A,Product_Master!B:B,"Not Found") -> Printer
A38: COUNTIFS lagao; kisi ek employee ko choose karo. | N38: =_xlfn.XLOOKUP(D17,Product_Master!A:A,Product_Master!B:B,"Not Found") -> Pen
A39: LEVEL 2 · INTERVIEW FAVORITE | N39: =_xlfn.XLOOKUP(D18,Product_Master!A:A,Product_Master!B:B,"Not Found") -> Office Chair
... A42: LEVEL 2 · DATA QUALITY | N42: =_xlfn.XLOOKUP(D21,Product_Master!A:A,Product_Master!B:B,"Not Found") -> Keyboard
A43: Q6. Employee Master mein extra spaces kaise remove karoge?
A44: TRIM lagao aur cleaned department name ko verify karo.

Sheet Employee_Master
A2: Table 2: Employee_Master
A3: Employee_ID | B3: Employee_Name | C3: Department | D3: Monthly_Target | E3: Manager
A4: E101 | B4: Rahul | C4: Sales | D4: 50000 | E4: Amit | H4: Practice: Employee ID se naam fetch karo, department-wise employee count nikalo, sales target vs achievement report banao aur TRIM se extra spaces clean karo
A5: E102 | B5: Priya | C5: Sales | D5: 60000 | E5: Amit
A6: E103 | B6: Amit | C6: Marketing | D6: 45000 | E6: Neha
A7: E104 | B7: Neha | C7: Sales | D7: 55000 | E7: Amit
A8: E105 | B8: Karan | C8: Finance | D8: 40000 | E8: Riya
A9: E106 | B9: Pooja | C9: Sales | D9: 65000 | E9: Amit

Sheet Product_Master
A2: Table 3: Product_Master
A3: Product_ID | B3: Product_Name | C3: Category | D3: Cost_Price
A4: P101 | B4: Laptop | C4: Electronics | D4: 900 | I4: Practice: Product ID se product name, category aur cost price fetch karo. Phir total cost aur profit calculate karo.
A5: P102 | B5: Monitor | C5: Electronics | D5: 1100
A6: P103 | B6: Keyboard | C6: Accessories | D6: 500
A7: P104 | B7: Mouse | C7: Accessories | D7: 350
A8: P105 | B8: Notebook | C8: Stationery | D8: 120
A9: P106 | B9: Printer | C9: Electronics | D9: 1800
A10: P107 | B10: Pen | C10: Stationery | D10: 50
A11: P108 | B11: Office Chair | C11: Furniture | D11: 2200

Sheet Sheet4
A2: Table 4: Sales_Data mein naye calculated columns
A3: Sales table mein original 9 columns ke baad ye columns add karna:
A4: Column | B4: Heading | C4: Formula in row 2 | K4: Excel mein proper structured tables kaise banayein
A5: J | B5: Gross_Sales | C5: =G2*H2 -> 0 | K5: 1. Har table ka data copy karke alag worksheet mein paste karo.
A6: K | B6: Discount_Amount | C6: =J2*I2 -> 0 | K6: 2. Data ke andar click karke Ctrl + T dabao.
A7: L | B7: Net_Sales | C7: =J2-K2 -> 0 | K7: 3. My table has headers ko tick karo.
A8: M | B8: Employee_Name | C8: =_xlfn.XLOOKUP(C2,Employee_Master!A:A,Employee_Master!B:B,"Not Found") -> 0 | K8: 4. Table Design mein jaakar table ka naam rakho: Sales_Data, Employee_Master aur Product_Master.
A9: N | B9: Product_Name | C9: =_xlfn.XLOOKUP(D2,Product_Master!A:A,Product_Master!B:B,"Not Found") -> 0 | K9: 5. Formulas ko first data row mein lagao; Excel Table mein aam taur par formula poore column mein automatically fill ho jayega.
A10: O | B10: Category | C10: =_xlfn.XLOOKUP(D2,Product_Master!A:A,Product_Master!C:C,"Not Found") -> 0 | K10: Interview tip: Ctrl + T se banaye gaye Excel Tables dynamic hote hain. Naya data add karne par table expand ho sakta hai aur structured references formulas ko readable banate hain.
A11: P | B11: Total_Cost | C11: =G2*_xlfn.XLOOKUP(D2,Product_Master!A:A,Product_Master!D:D,0) -> 0
A12: Q | B12: Profit | C12: =L2-P2 -> 0
A13: R | B13: Month | C13: =TEXT(B2,"mmm") -> Jan
A14: S | B14: Order_Status | C14: =IF(L2>=10000,"High Value","Normal") -> Normal
